setup.py
adjusty/__init__.py
adjusty/adjust_api.py
adjusty.egg-info/PKG-INFO
adjusty.egg-info/SOURCES.txt
adjusty.egg-info/dependency_links.txt
adjusty.egg-info/not-zip-safe
adjusty.egg-info/requires.txt
adjusty.egg-info/top_level.txt