Metadata-Version: 1.1
Name: adjusty
Version: 1.1
Summary: A Simplified Python implementation of Adjust API for the KPI service
Home-page: http://github.com/techieashish/adjusty
Author: Ashish Srivastava
Author-email: ashisharivastava1872@gmail.com
License: UNKNOWN
Keywords: python adjust api nextadjust
Platform: UNKNOWN
Classifier: Development Status :: 5 - Production/Stable
Classifier: Programming Language :: Python :: 3
